pil_helper/__init__.py
pil_helper/utils/__init__.py
pil_helper/utils/draw.py
pil_helper-0.0.7.dist-info/METADATA
pil_helper-0.0.7.dist-info/WHEEL
pil_helper-0.0.7.dist-info/top_level.txt
pil_helper-0.0.7.dist-info/RECORD
