Metadata-Version: 2.1
Name: pil-helper
Version: 0.0.7
Summary: Pil helper
Home-page: https://github.com/automatethem/pil-helper
Author: Sang Ki Kwon
Author-email: automatethem@gmail.com
License: MIT
Platform: UNKNOWN
